cnpj_field/__init__.py
cnpj_field/forms.py
cnpj_field/models.py
cnpj_field/validators.py
django_CNPJField-1.dist-info/LICENSE
django_CNPJField-1.dist-info/METADATA
django_CNPJField-1.dist-info/WHEEL
django_CNPJField-1.dist-info/top_level.txt
django_CNPJField-1.dist-info/RECORD
