Metadata-Version: 2.1
Name: django-CNPJField
Version: 1
Summary: Validador de CNPJ para Django
Home-page: https://github.com/kadius/django-cnpjfield
Author: GABRIEL GUERRA
Author-email: gabrielguerra@unigranrio.br
License: UNKNOWN
Platform: UNKNOWN
Classifier: Programming Language :: Python :: 3
Classifier: License :: OSI Approved :: MIT License
Classifier: Operating System :: OS Independent
Requires-Python: >=3.8
